huaweicloudsdkvpcep/__init__.py
huaweicloudsdkvpcep/v1/__init__.py
huaweicloudsdkvpcep/v1/vpcep_async_client.py
huaweicloudsdkvpcep/v1/vpcep_client.py
huaweicloudsdkvpcep/v1/model/__init__.py
huaweicloudsdkvpcep/v1/model/accept_or_reject_endpoint_request.py
huaweicloudsdkvpcep/v1/model/accept_or_reject_endpoint_request_body.py
huaweicloudsdkvpcep/v1/model/accept_or_reject_endpoint_response.py
huaweicloudsdkvpcep/v1/model/add_endpoint_service_server_resource_request.py
huaweicloudsdkvpcep/v1/model/add_endpoint_service_server_resource_request_body.py
huaweicloudsdkvpcep/v1/model/add_endpoint_service_server_resource_response.py
huaweicloudsdkvpcep/v1/model/add_or_remove_service_permissions_request.py
huaweicloudsdkvpcep/v1/model/add_or_remove_service_permissions_request_body.py
huaweicloudsdkvpcep/v1/model/add_or_remove_service_permissions_response.py
huaweicloudsdkvpcep/v1/model/batch_add_endpoint_service_permissions_request.py
huaweicloudsdkvpcep/v1/model/batch_add_endpoint_service_permissions_request_body.py
huaweicloudsdkvpcep/v1/model/batch_add_endpoint_service_permissions_response.py
huaweicloudsdkvpcep/v1/model/batch_add_or_remove_resource_instance_request.py
huaweicloudsdkvpcep/v1/model/batch_add_or_remove_resource_instance_request_body.py
huaweicloudsdkvpcep/v1/model/batch_add_or_remove_resource_instance_response.py
huaweicloudsdkvpcep/v1/model/batch_remove_endpoint_service_permissions_request.py
huaweicloudsdkvpcep/v1/model/batch_remove_endpoint_service_permissions_request_body.py
huaweicloudsdkvpcep/v1/model/batch_remove_endpoint_service_permissions_response.py
huaweicloudsdkvpcep/v1/model/connection_endpoints.py
huaweicloudsdkvpcep/v1/model/connections_desc.py
huaweicloudsdkvpcep/v1/model/create_endpoint_request.py
huaweicloudsdkvpcep/v1/model/create_endpoint_request_body.py
huaweicloudsdkvpcep/v1/model/create_endpoint_response.py
huaweicloudsdkvpcep/v1/model/create_endpoint_service_request.py
huaweicloudsdkvpcep-3.1.184.dist-info/METADATA
huaweicloudsdkvpcep-3.1.184.dist-info/WHEEL
huaweicloudsdkvpcep-3.1.184.dist-info/licenses/LICENSE
huaweicloudsdkvpcep-3.1.184.dist-info/RECORD
